lumerpy/.idea/inspectionProfiles/profiles_settings.xml
lumerpy/.idea/inspectionProfiles/Project_Default.xml
lumerpy/.idea/lumerpy.iml
lumerpy/.idea/modules.xml
lumerpy/__init__.py
lumerpy/console.py
lumerpy/console_copy.py
lumerpy/data_process.py
lumerpy/diffrann_datas.py
lumerpy/diffrann_diffrann.py
lumerpy/diffrann_logic_func.py
lumerpy/diffrann_plots.py
lumerpy/donn.py
lumerpy/eri.py
lumerpy/fdtd_manager.py
lumerpy/initialize.py
lumerpy/monitor.py
lumerpy/rect.py
lumerpy/simulation.py
lumerpy/source.py
lumerpy/temp.fsp
lumerpy/tools.py
lumerpy-1.6.4.dist-info/licenses/LICENSE.txt
lumerpy-1.6.4.dist-info/METADATA
lumerpy-1.6.4.dist-info/WHEEL
lumerpy-1.6.4.dist-info/RECORD
