Metadata-Version: 2.4
Name: lumerpy
Version: 1.6.4
Summary: A Python package that provides a secondary wrapper for the official Python API of the optical simulation software Lumerical, enabling easier usage in more complex scenarios.
License: MIT
License-File: LICENSE.txt
Author: OscarxChen
Author-email: oscarxchen@outlook.com
Requires-Python: >=3.7
Classifier: License :: OSI Approved :: MIT License
Classifier: Programming Language :: Python :: 3
Classifier: Programming Language :: Python :: 3.7
Classifier: Programming Language :: Python :: 3.8
Classifier: Programming Language :: Python :: 3.9
Classifier: Programming Language :: Python :: 3.10
Classifier: Programming Language :: Python :: 3.11
Classifier: Programming Language :: Python :: 3.12
Classifier: Programming Language :: Python :: 3.13
Classifier: Programming Language :: Python :: 3.14
Requires-Dist: matplotlib
Requires-Dist: numpy
Project-URL: Homepage, https://github.com/oscarxchen/lumerpy
Project-URL: Repository, https://github.com/oscarxchen/lumerpy
